package/__init__.py
package/helloWorld.py
istra_hw2package-0.2.4.dist-info/METADATA
istra_hw2package-0.2.4.dist-info/WHEEL
istra_hw2package-0.2.4.dist-info/top_level.txt
istra_hw2package-0.2.4.dist-info/RECORD
