Metadata-Version: 2.1
Name: istra-hw2package
Version: 0.2.4
Summary: Package for hw2
Home-page: UNKNOWN
Author: Istratov_N
Author-email: UNKNOWN
License: MIT
Keywords: hello_world datetime
Platform: UNKNOWN
Classifier: Development Status :: 3 - Alpha
Classifier: License :: OSI Approved :: MIT License
Classifier: Programming Language :: Python :: 3
Classifier: Programming Language :: Python :: 3.6
Classifier: Programming Language :: Python :: 3.7
Classifier: Topic :: Text Processing :: Linguistic
Requires-Dist: Flask
